robust/__init__.py
robust/admin.py
robust/apps.py
robust/beat.py
robust/exceptions.py
robust/models.py
robust/receivers.py
robust/runners.py
robust/signals.py
robust/worker.py
robust/management/__init__.py
robust/management/commands/__init__.py
robust/management/commands/robust_beat.py
robust/management/commands/robust_worker.py
robust/migrations/0001_initial.py
robust/migrations/0002_task_retries.py
robust/migrations/0003_traceback.py
robust/migrations/0004_delete_ratelimitrun.py
robust/migrations/__init__.py
robust/templates/admin/robust/change_form.html
robust/templates/admin/robust/change_list.html
robust/templates/admin/robust/task/change_form.html
robust/tests/__init__.py
robust/tests/test_basic.py
robust/tests/test_tags.py
django_robust-0.3.0.dist-info/METADATA
django_robust-0.3.0.dist-info/WHEEL
django_robust-0.3.0.dist-info/top_level.txt
django_robust-0.3.0.dist-info/RECORD
