Metadata-Version: 2.1
Name: django-robust
Version: 0.3.0
Summary: robust background queue for django
Home-page: https://github.com/barbuza/django-robust
Author: Victor Kotseruba
Author-email: barbuzaster@gmail.com
License: UNKNOWN
Platform: UNKNOWN
Requires-Python: >=3.6
Requires-Dist: django-object-actions
Requires-Dist: django-redis
Requires-Dist: django (>=2.0)
Requires-Dist: psycopg2
Requires-Dist: pygments
Requires-Dist: redis
Requires-Dist: schedule
